[
  {
    "domain": "akhileshthite.github.io",
    "public": true,
    "protocols": {
      "http": true,
      "hyper": true,
      "ipfs": true
    },
    "id": "akhileshthite.github.io",
    "links": {
      "http": {
        "enabled": true,
        "link": "https://akhileshthite.github.io"
      },
      "hyper": {
        "enabled": true,
        "link": "hyper://akhileshthite.github.io",
        "gateway": "https://akhileshthite-github-io.hyper.hypha.coop/",
        "raw": "hyper://7ns6qwpwiqt987p61qxice51m1h1c184eutw5pwg1kw4hio6m4qo/",
        "dnslink": "/hyper/7ns6qwpwiqt987p61qxice51m1h1c184eutw5pwg1kw4hio6m4qo/"
      },
      "ipfs": {
        "enabled": true,
        "link": "ipns://akhileshthite.github.io/",
        "gateway": "https://akhileshthite-github-io.ipns.ipfs.hypha.coop",
        "cid": "bafybeibmtkvecjm4mtcrcy3xfsh7wz3ujfkeisv3hmqrqx7pd7wvhvts2e",
        "pubKey": "ipns://k51qzi5uqu5dizdcam91hmz70hm1xkrz9o3ox18hodzx0m7mnwmve4jo8397wn/",
        "dnslink": "/ipns/k51qzi5uqu5dizdcam91hmz70hm1xkrz9o3ox18hodzx0m7mnwmve4jo8397wn/"
      }
    }
  },
  {
    "domain": "brasil.dweb.camp.",
    "protocols": {
      "http": false,
      "ipfs": true,
      "hyper": true
    },
    "public": true,
    "id": "brasil.dweb.camp.",
    "links": {
      "http": {
        "enabled": true,
        "link": "https://brasil.dweb.camp."
      },
      "hyper": {
        "enabled": true,
        "link": "hyper://brasil.dweb.camp.",
        "gateway": "https://brasil-dweb-camp-.hyper.hypha.coop/",
        "raw": "hyper://sks76guzmwyofganijtxoqfk7gt9zpj16j157utbwxmdkox8nsro/",
        "dnslink": "/hyper/sks76guzmwyofganijtxoqfk7gt9zpj16j157utbwxmdkox8nsro/"
      },
      "ipfs": {
        "enabled": true,
        "link": "ipns://brasil.dweb.camp./",
        "gateway": "https://brasil-dweb-camp-.ipns.ipfs.hypha.coop",
        "cid": "bafybeib44swz34oivqhbq2a2y7ldkqej4f7bfmldqr273zhdb47bqy5nau",
        "pubKey": "ipns://k51qzi5uqu5djav1q2ccpd2hv7ly77rdu6k4hlpe2f0a7lgbustrm1aorris3q/",
        "dnslink": "/ipns/k51qzi5uqu5djav1q2ccpd2hv7ly77rdu6k4hlpe2f0a7lgbustrm1aorris3q/"
      }
    }
  },
  {
    "domain": "ciudadradio",
    "protocols": {
      "http": false,
      "ipfs": true,
      "hyper": true
    },
    "public": true,
    "id": "ciudadradio",
    "links": {
      "http": {
        "enabled": true,
        "link": "https://ciudadradio"
      },
      "hyper": {
        "enabled": true,
        "link": "hyper://ciudadradio",
        "gateway": "https://ciudadradio.hyper.hypha.coop/",
        "raw": "hyper://ska5u5kemghhfe5hmwq36bs14tbn1mupsbp9rgsu837xt8pg6tby/",
        "dnslink": "/hyper/ska5u5kemghhfe5hmwq36bs14tbn1mupsbp9rgsu837xt8pg6tby/"
      },
      "ipfs": {
        "enabled": true,
        "link": "ipns://ciudadradio/",
        "gateway": "https://ciudadradio.ipns.ipfs.hypha.coop",
        "cid": "bafybeibanxkvkd74z4stdjk4svb347kf7lvhruz6j42myxuy7us3gtxkhe",
        "pubKey": "ipns://k51qzi5uqu5dganf2rf30wyrdn15wswtsjmi8wk2o2vsb6wo5pmxuerf4floj7/",
        "dnslink": "/ipns/k51qzi5uqu5dganf2rf30wyrdn15wswtsjmi8wk2o2vsb6wo5pmxuerf4floj7/"
      }
    }
  },
  {
    "domain": "dp.akhilesh.art",
    "public": true,
    "protocols": {
      "http": true,
      "hyper": true,
      "ipfs": true
    },
    "id": "dp.akhilesh.art",
    "links": {
      "http": {
        "enabled": true,
        "link": "https://dp.akhilesh.art"
      },
      "hyper": {
        "enabled": true,
        "link": "hyper://dp.akhilesh.art",
        "gateway": "https://dp-akhilesh-art.hyper.hypha.coop/",
        "raw": "hyper://t685fd3snbadhqkss8spcgz454p95ap77kdfjafotsxfhhrhuqio/",
        "dnslink": "/hyper/t685fd3snbadhqkss8spcgz454p95ap77kdfjafotsxfhhrhuqio/"
      },
      "ipfs": {
        "enabled": true,
        "link": "ipns://dp.akhilesh.art/",
        "gateway": "https://dp-akhilesh-art.ipns.ipfs.hypha.coop",
        "cid": "bafybeibhq4pwulmelo3hii4osasuomegzrj5qdiuqa63sqgjymkx4fvoue",
        "pubKey": "ipns://k51qzi5uqu5djj6yo1nne5r2oomxgroy3tezhgupvx0v2jlbighfah1k028sc1/",
        "dnslink": "/ipns/k51qzi5uqu5djj6yo1nne5r2oomxgroy3tezhgupvx0v2jlbighfah1k028sc1/"
      }
    }
  },
  {
    "domain": "post.postvis.io",
    "public": true,
    "protocols": {
      "http": true,
      "hyper": true,
      "ipfs": true
    },
    "id": "post.postvis.io",
    "links": {
      "http": {
        "enabled": true,
        "link": "https://post.postvis.io"
      },
      "ipfs": {
        "enabled": true,
        "link": "ipns://post.postvis.io/",
        "gateway": "https://post-postvis-io.ipns.ipfs.hypha.coop",
        "cid": "bafybeiczsscdsbs7ffqz55asqdf3smv6klcw3gofszvwlyarci47bgf354",
        "pubKey": "ipns://k51qzi5uqu5dkjbv5x8qeh6p7xmszrdb4f6iutruikqqwauftlkh89dhhr2svo/",
        "dnslink": "/ipns/k51qzi5uqu5dkjbv5x8qeh6p7xmszrdb4f6iutruikqqwauftlkh89dhhr2svo/"
      },
      "hyper": {
        "enabled": true,
        "link": "hyper://post.postvis.io",
        "gateway": "https://post-postvis-io.hyper.hypha.coop/",
        "raw": "hyper://id5fio4pkxuzfgdik3m1dq8aqawsz4anjj5k4c4knh96qko9ri9y/",
        "dnslink": "/hyper/id5fio4pkxuzfgdik3m1dq8aqawsz4anjj5k4c4knh96qko9ri9y/"
      }
    }
  },
  {
    "domain": "manual-site-1.com",
    "metadata": {
      "title": "Manually Added Site",
      "description": "This site was added manually."
    },
    "links": {
      "http": {
        "enabled": true,
        "link": "http://manual-site-1.com"
      },
      "hyper": {
        "enabled": false
      },
      "ipfs": {
        "enabled": false
      }
    },
    "public": true
  }
]